spotify_tracker/__init__.py
spotify_tracker/config.py
spotify_tracker/current_track.py
spotify_tracker/favorites_client.py
spotify_tracker/runner.py
spotify_tracker/spotify_client.py
spotify_tracker/watcher_client.py
spotifytracker-0.0.18.dist-info/METADATA
spotifytracker-0.0.18.dist-info/RECORD
spotifytracker-0.0.18.dist-info/WHEEL
spotifytracker-0.0.18.dist-info/entry_points.txt
spotifytracker-0.0.18.dist-info/top_level.txt
