Metadata-Version: 2.1
Name: spotifytracker
Version: 0.0.18
Summary: Track your Spotify play history.
Home-page: http://github.com/eriktaubeneck/spotifytracker
Author: Erik Taubeneck
Author-email: erik.taubeneck@gmail.com
License: MIT
Platform: OS X
Classifier: Development Status :: 3 - Alpha
Classifier: Environment :: Plugins
Classifier: Environment :: Web Environment
Classifier: Framework :: Flask
Classifier: Intended Audience :: Developers
Classifier: License :: OSI Approved :: MIT License
Classifier: Natural Language :: English
Classifier: Operating System :: MacOS :: MacOS X
Classifier: Programming Language :: Python
Classifier: Programming Language :: Python :: 3
Requires-Dist: pyyaml (<4.a0,>=3.0)
Requires-Dist: docopt (<0.7.0,>=0.6.0)
Requires-Dist: spotipy (<2.4.0,>=2.3.7)
Requires-Dist: arrow (<1.0.0,>0.7.0)
